[{
    "numberOfPeople": 1,
    "one_meal": "₹3150",
    "one_meal_breakfast": "₹3500",
    "two_meals": "₹4250",
    "two_meals_breakfast": "₹4300"
  },
  {
    "numberOfPeople": 2,
    "one_meal": "₹3750",
    "one_meal_breakfast": "₹4300",
    "two_meals": "₹5850",
    "two_meals_breakfast": "₹5400"
  },
  {
    "numberOfPeople": 3,
    "one_meal": "₹4850",
    "one_meal_breakfast": "₹5400",
    "two_meals": "₹6500",
    "two_meals_breakfast": "₹6950"
  },
  {
    "numberOfPeople": 4,
    "one_meal": "₹5450",
    "one_meal_breakfast": "₹6550",
    "two_meals": "₹8050",
    "two_meals_breakfast": "₹7600"
  },
  {
    "numberOfPeople": 5,
    "one_meal": "₹6550",
    "one_meal_breakfast": "₹7650",
    "two_meals": "₹9650",
    "two_meals_breakfast": "₹9200"
  }
]